.gitignore
.project
.pydevproject
CHANGELOG
LICENSE
MANIFEST.in
README.md
setup.py
.settings/org.eclipse.core.resources.prefs
pyrla/__init__.py
pyrla/pyrla.py
pyrla.egg-info/PKG-INFO
pyrla.egg-info/SOURCES.txt
pyrla.egg-info/dependency_links.txt
pyrla.egg-info/entry_points.txt
pyrla.egg-info/not-zip-safe
pyrla.egg-info/top_level.txt
pyrla/examples/input/foobar
pyrla/examples/input/input_example
pyrla/examples/jinja/foobar
pyrla/examples/jinja/input_example
pyrla/examples/modifiers/input_example