Metadata-Version: 2.1
Name: pyrla
Version: 0.1.0
Summary: A simple tool to launch multiple processes 
Home-page: https://github.com/lorenzo-rovigatti/pyrla
Author: Lorenzo Rovigatti
Author-email: lorenzo.rovigatti@uniroma1.it
License: GNU GPL 3.0
Platform: UNKNOWN
Classifier: Development Status :: 5 - Production/Stable
Classifier: Environment :: Console
Classifier: Intended Audience :: Science/Research
Classifier: License :: OSI Approved :: GNU General Public License v3 (GPLv3)
Classifier: Operating System :: OS Independent
Classifier: Programming Language :: Python
License-File: LICENSE
